otplib/__init__.py
otplib/otplib.py
otplib-0.3.0.dist-info/METADATA
otplib-0.3.0.dist-info/WHEEL
otplib-0.3.0.dist-info/entry_points.txt
otplib-0.3.0.dist-info/top_level.txt
otplib-0.3.0.dist-info/RECORD
