Metadata-Version: 2.1
Name: otplib
Version: 0.3.0
Summary: send otp
Home-page: https://github.com/sanjaymarison/otplib
Author: SanjayMarison
Author-email: sanjaymarison@gmail.com
License: MIT
Platform: UNKNOWN
Classifier: License :: OSI Approved :: MIT License
Classifier: Programming Language :: Python :: 3
Classifier: Programming Language :: Python :: 3.5
Classifier: Programming Language :: Python :: 3.6
Classifier: Programming Language :: Python :: 3.7
Classifier: Programming Language :: Python :: 3.8
